{"status":200,"headers":{"server":"openresty/1.15.8.2","date":"Mon, 01 May 2023 06:30:18 GMT","content-type":"application/json","transfer-encoding":"chunked","connection":"close","vary":"Accept-Encoding","strict-transport-security":"max-age=15724800; includeSubDomains"},"data":{"metricInput":{"metricId":"storage_tableSchema","metricPeriod":"REAL_TIME","databaseName":"udprodsql/db-prod","databaseType":"SQLSERVER","tableName":"seller_order","from":null,"to":null,"recommendationRequired":false},"metricOutput":{"result":{"queryList":[{"columnName":"serial_no","createdDate":"2022-01-14 17:21:48.66","ordinalPosition":1,"columnDefault":null,"dataType":"nvarchar","characterMaximumLength":100,"collationName":"SQL_Latin1_General_CP1_CI_AS","rowGuid":false,"nullable":false,"identity":false},{"columnName":"order_id","createdDate":"2022-01-14 17:21:48.66","ordinalPosition":2,"columnDefault":null,"dataType":"nvarchar","characterMaximumLength":100,"collationName":"SQL_Latin1_General_CP1_CI_AS","rowGuid":false,"nullable":false,"identity":false},{"columnName":"created_at","createdDate":"2022-01-14 17:21:48.66","ordinalPosition":3,"columnDefault":"(getdate())","dataType":"datetime2","characterMaximumLength":null,"collationName":null,"rowGuid":false,"nullable":false,"identity":false},{"columnName":"updated_at","createdDate":"2022-01-14 17:21:48.66","ordinalPosition":4,"columnDefault":null,"dataType":"timestamp","characterMaximumLength":null,"collationName":null,"rowGuid":false,"nullable":false,"identity":false},{"columnName":"total_order_sp_paise","createdDate":"2022-01-14 17:21:48.66","ordinalPosition":5,"columnDefault":"(NULL)","dataType":"bigint","characterMaximumLength":null,"collationName":null,"rowGuid":false,"nullable":true,"identity":false},{"columnName":"total_payment_charge_paise","createdDate":"2022-01-14 17:21:48.66","ordinalPosition":6,"columnDefault":"(NULL)","dataType":"bigint","characterMaximumLength":null,"collationName":null,"rowGuid":false,"nullable":true,"identity":false},{"columnName":"total_shipping_cost_paise","createdDate":"2022-01-14 17:21:48.66","ordinalPosition":7,"columnDefault":"(NULL)","dataType":"bigint","characterMaximumLength":null,"collationName":null,"rowGuid":false,"nullable":true,"identity":false},{"columnName":"buyer_id","createdDate":"2022-01-14 17:21:48.66","ordinalPosition":8,"columnDefault":"('')","dataType":"nvarchar","characterMaximumLength":100,"collationName":"SQL_Latin1_General_CP1_CI_AS","rowGuid":false,"nullable":true,"identity":false},{"columnName":"seller_id","createdDate":"2022-01-14 17:21:48.66","ordinalPosition":9,"columnDefault":"('')","dataType":"nvarchar","characterMaximumLength":100,"collationName":"SQL_Latin1_General_CP1_CI_AS","rowGuid":false,"nullable":true,"identity":false},{"columnName":"current_active","createdDate":"2022-01-14 17:21:48.66","ordinalPosition":10,"columnDefault":"('1')","dataType":"tinyint","characterMaximumLength":null,"collationName":null,"rowGuid":false,"nullable":true,"identity":false},{"columnName":"sample_order","createdDate":"2022-01-14 17:21:48.66","ordinalPosition":11,"columnDefault":"((0))","dataType":"tinyint","characterMaximumLength":null,"collationName":null,"rowGuid":false,"nullable":true,"identity":false},{"columnName":"order_status","createdDate":"2022-01-14 17:21:48.66","ordinalPosition":12,"columnDefault":"(NULL)","dataType":"nvarchar","characterMaximumLength":100,"collationName":"SQL_Latin1_General_CP1_CI_AS","rowGuid":false,"nullable":true,"identity":false},{"columnName":"main_order_id","createdDate":"2022-01-14 17:21:48.66","ordinalPosition":13,"columnDefault":null,"dataType":"nvarchar","characterMaximumLength":40,"collationName":"SQL_Latin1_General_CP1_CI_AS","rowGuid":false,"nullable":true,"identity":false},{"columnName":"extra_data","createdDate":"2022-01-14 17:21:48.66","ordinalPosition":14,"columnDefault":null,"dataType":"nvarchar","characterMaximumLength":2048,"collationName":"SQL_Latin1_General_CP1_CI_AS","rowGuid":false,"nullable":true,"identity":false},{"columnName":"order_type","createdDate":"2022-01-14 17:21:48.66","ordinalPosition":15,"columnDefault":"('FORWARD')","dataType":"nvarchar","characterMaximumLength":16,"collationName":"SQL_Latin1_General_CP1_CI_AS","rowGuid":false,"nullable":false,"identity":false},{"columnName":"last_updated_at","createdDate":"2022-01-14 17:21:48.66","ordinalPosition":16,"columnDefault":"(getdate())","dataType":"datetime2","characterMaximumLength":null,"collationName":null,"rowGuid":false,"nullable":false,"identity":false},{"columnName":"order_parties","createdDate":"2022-01-14 17:21:48.66","ordinalPosition":17,"columnDefault":null,"dataType":"nvarchar","characterMaximumLength":2048,"collationName":"SQL_Latin1_General_CP1_CI_AS","rowGuid":false,"nullable":true,"identity":false},{"columnName":"order_meta_info","createdDate":"2022-01-14 17:21:48.66","ordinalPosition":18,"columnDefault":"(NULL)","dataType":"nvarchar","characterMaximumLength":2048,"collationName":"SQL_Latin1_General_CP1_CI_AS","rowGuid":false,"nullable":true,"identity":false},{"columnName":"platform_id","createdDate":"2022-01-14 17:21:48.66","ordinalPosition":19,"columnDefault":"(NULL)","dataType":"nvarchar","characterMaximumLength":100,"collationName":"SQL_Latin1_General_CP1_CI_AS","rowGuid":false,"nullable":true,"identity":false}]},"recommendation":null},"metadata":{"underlyingQueries":["SELECT\no.create_date as createdDate,\nc.is_rowguidcol as isRowGuid,\nc.is_identity as isIdentity,\nc.name AS columnName,\nCOLUMNPROPERTY(c.object_id, c.name, 'ordinal') AS ordinalPosition,\nconvert(nvarchar(4000),\nOBJECT_DEFINITION(c.default_object_id)) AS columnDefault,\nconvert(Bit, CASE c.is_nullable\nWHEN 1 THEN 1 ELSE 0 END) AS isNullable,\nISNULL(TYPE_NAME(c.system_type_id), t.name) AS dataType,\nCOLUMNPROPERTY(c.object_id, c.name, 'charmaxlen') AS characterMaximumLength,\nc.collation_name AS collationName\nFROM\nsys.objects o JOIN sys.columns c ON c.object_id = o.object_id\nLEFT JOIN sys.types t ON c.user_type_id = t.user_type_id\nWHERE\no.type IN ('U', 'V') and o.name = :tableName "],"referenceDocumentation":[],"description":"","supportsHistorical":false,"minimumRepeatInterval":""}}}
