{"status":200,"headers":{"server":"openresty/1.15.8.2","date":"Mon, 01 May 2023 06:28:29 GMT","content-type":"application/json","transfer-encoding":"chunked","connection":"close","vary":"Accept-Encoding","strict-transport-security":"max-age=15724800; includeSubDomains"},"data":{"metricInput":{"metricId":"performance_readReplicationLag","metricPeriod":"REAL_TIME","databaseType":"SQLSERVER","databaseName":"udprodsql/db-prod","replicaDatabaseName":"udprodsql/db-prod-readonly","from":null,"to":null,"recommendationRequired":true},"metricOutput":{"result":{"queryList":[{"lastRedoneTimeInMillis":1682902709000,"lastReceivedTimeInMillis":1682902709000,"replicationLagInMillis":0}]},"recommendation":{"text":"No significant replication lag. No action required.","actionRequired":false}},"metadata":{"underlyingQueries":["SELECT * FROM sys.dm_database_replica_states"],"referenceDocumentation":["https://docs.microsoft.com/en-us/sql/relational-databases/system-dynamic-management-views/sys-dm-database-replica-states-azure-sql-database?view=sql-server-ver16"],"description":"Returns a row for the database, exposing state for the local replica.","supportsHistorical":false,"minimumRepeatInterval":"","supportsAlert":true,"supportedAlerts":["alert_readReplicationLag"]}}}
